webtranspose/__init__.py
webtranspose/chat.py
webtranspose/crawl.py
webtranspose/openai.py
webtranspose/scrape.py
webtranspose/search.py
webtranspose/webt_api.py
webtranspose-0.3.2.dist-info/LICENSE.rst
webtranspose-0.3.2.dist-info/METADATA
webtranspose-0.3.2.dist-info/WHEEL
webtranspose-0.3.2.dist-info/RECORD
