Metadata-Version: 2.1
Name: webtranspose
Version: 0.3.2
Summary: Reliable APIs for the website data
Home-page: https://github.com/mike-gee/webtranspose
Keywords: webtranspose
Author: Mike Gee
Author-email: mike@webtranspose.com
Requires-Python: >=3.8,<3.12
Classifier: Development Status :: 2 - Pre-Alpha
Classifier: Intended Audience :: Developers
Classifier: License :: OSI Approved :: GNU Affero General Public License v3 or later (AGPLv3+)
Classifier: Natural Language :: English
Classifier: Programming Language :: Python :: 3
Classifier: Programming Language :: Python :: 3.8
Classifier: Programming Language :: Python :: 3.9
Classifier: Programming Language :: Python :: 3.10
Classifier: Programming Language :: Python :: 3.11
Requires-Dist: bs4 (>=0.0.1,<0.0.2)
Requires-Dist: httpx (>=0.25.1,<0.26.0)
Requires-Dist: lxml (>=4.9.3,<5.0.0)
Requires-Dist: openai (>=1.3.3,<2.0.0)
Requires-Dist: requests (>=2.31.0,<3.0.0)
Requires-Dist: tiktoken (>=0.5.1,<0.6.0)
Project-URL: Bug Tracker, https://github.com/mike-gee/webtranspose/issues
Project-URL: Documentation, https://docs.webtranspose.com
Project-URL: Repository, https://github.com/mike-gee/webtranspose
